foritech/__init__.py
foritech/__main__.py
foritech/api.py
foritech/errors.py
foritech/key_utils.py
foritech/models.py
foritech/x509_utils.py
foritech/cli/__init__.py
foritech/cli/__main__.py
foritech/cli/add_keys_verify.py
foritech/cli/main.py
foritech/crypto/__init__.py
foritech/crypto/combiners.py
foritech/crypto/hybrid_sig.py
foritech/crypto/hybrid_wrap.py
foritech/crypto/json_bundle.py
foritech/crypto/pqc_kem.py
foritech/crypto/stream_core.py
foritech/crypto/unwrap_core.py
foritech/crypto/wrap_core.py
foritech/pki/__init__.py
foritech/pki/x509_tools.py
foritech/tlspqc/__init__.py
foritech/tlspqc/session.py
foritech_cli/main.py
foritech_sdk-0.1.3.dist-info/licenses/LICENSE
foritech_sdk-0.1.3.dist-info/METADATA
foritech_sdk-0.1.3.dist-info/WHEEL
foritech_sdk-0.1.3.dist-info/entry_points.txt
foritech_sdk-0.1.3.dist-info/top_level.txt
foritech_sdk-0.1.3.dist-info/RECORD
