Metadata-Version: 2.4
Name: foritech-sdk
Version: 0.1.3
Summary: Python SDK for Foritech Secure System.
Author-email: Foritech <forrybg.hh@gmail.com>
License: MIT
Project-URL: Homepage, https://github.com/foritech-secure-system/foritech-secure-system
Project-URL: Issues, https://github.com/foritech-secure-system/foritech-secure-system/issues
Project-URL: Source, https://github.com/foritech-secure-system/foritech-secure-system
Classifier: Development Status :: 4 - Beta
Classifier: Intended Audience :: Developers
Classifier: License :: OSI Approved :: MIT License
Classifier: Programming Language :: Python
Classifier: Programming Language :: Python :: 3
Classifier: Programming Language :: Python :: 3 :: Only
Classifier: Programming Language :: Python :: 3.11
Classifier: Programming Language :: Python :: 3.12
Classifier: Programming Language :: Python :: 3.13
Classifier: Operating System :: OS Independent
Classifier: Topic :: Security :: Cryptography
Requires-Python: >=3.11
License-File: LICENSE
Requires-Dist: cryptography>=42
Provides-Extra: dev
Requires-Dist: pytest; extra == "dev"
Requires-Dist: ruff; extra == "dev"
Requires-Dist: mypy; extra == "dev"
Dynamic: license-file
